setup.cfg
setup.py
sanic_admin/__init__.py
sanic_admin/entry_point.py
sanic_admin/reload.py
sanic_admin/urls.py
sanic_admin.egg-info/PKG-INFO
sanic_admin.egg-info/SOURCES.txt
sanic_admin.egg-info/dependency_links.txt
sanic_admin.egg-info/entry_points.txt
sanic_admin.egg-info/requires.txt
sanic_admin.egg-info/top_level.txt