Metadata-Version: 1.1
Name: sanic-admin
Version: 0.0.6
Summary: sanic-admin is a command line tool for automatically restarting sanic.
Home-page: https://github.com/38elements/sanic-admin
Author: 38elements
Author-email: UNKNOWN
License: MIT License
Keywords: sanic
Platform: UNKNOWN
Classifier: Development Status :: 3 - Alpha
Classifier: Programming Language :: Python :: 3.5
Classifier: Programming Language :: Python :: 3.6
Classifier: License :: OSI Approved :: MIT License
Classifier: Intended Audience :: Developers
